awktutorial/__init__.py
awktutorial/awk_tutorial.css
awktutorial/awk_tutorial.py
awktutorial/example_files/c1.txt
awktutorial/example_files/c2.txt
awktutorial/example_files/dept.txt
awktutorial/example_files/greeting.txt
awktutorial/example_files/items.csv
awktutorial/example_files/marks.txt
awktutorial/example_files/purchases.txt
awktutorial/example_files/table.txt
awktutorial/example_files/uniform.txt
awktutorial/tutorial/awk_00.md
awktutorial/tutorial/awk_01.md
awktutorial/tutorial/awk_02.md
awktutorial/tutorial/awk_03.md
awktutorial/tutorial/awk_04.md
awktutorial/tutorial/awk_05.md
awktutorial/tutorial/awk_06.md
awktutorial/tutorial/awk_07.md
awktutorial/tutorial/awk_08.md
awktutorial/tutorial/awk_09.md
awktutorial/tutorial/awk_10.md
awktutorial-1.6.0.dist-info/METADATA
awktutorial-1.6.0.dist-info/WHEEL
awktutorial-1.6.0.dist-info/entry_points.txt
awktutorial-1.6.0.dist-info/licenses/LICENSE
awktutorial-1.6.0.dist-info/RECORD
