Metadata-Version: 2.4
Name: awktutorial
Version: 1.6.0
Summary: brief tour of the GNU awk command
Project-URL: Source, https://github.com/learnbyexample/TUI-apps/tree/main/AwkTutorial
Project-URL: Issues, https://github.com/learnbyexample/TUI-apps/issues
Author-email: Sundeep Agarwal <learnbyexample.net@gmail.com>
License-File: LICENSE
Classifier: License :: OSI Approved :: MIT License
Classifier: Operating System :: OS Independent
Classifier: Programming Language :: Python :: 3
Requires-Python: >=3.9
Requires-Dist: textual==0.85.2
